README.md
setup.py
tempocalculation/__init__.py
tempocalculation/somePythonPack.py
tempocalculation.egg-info/PKG-INFO
tempocalculation.egg-info/SOURCES.txt
tempocalculation.egg-info/dependency_links.txt
tempocalculation.egg-info/requires.txt
tempocalculation.egg-info/top_level.txt