Metadata-Version: 1.0
Name: tempocalculation
Version: 0.1
Summary: A package to retrieve Scholarly Metadata
Home-page: https://github.com/ameyakarnad/ameya-sample-package
Author: Edlab
Author-email: ameyakarnadbvb@gmail.com
License: GNU
Platform: UNKNOWN
